Workbook

Sheet How to Use
A1: iGEM Self-Funding Budget Calculator — How to Use
A3: What this is | B3: A companion tool to the "How to Self-Fund for iGEM" contribution (Madrid-UCM, iGEM 2026). It turns Section 1 of that guide into a live, editable budget.
A4: Colour code | B4: Yellow cells with blue text = numbers you type in. Black text = formulas that update automatically — do not overwrite these.
A5: Sheet order | B5: 1) Registration 2) Lab Budget 3) Travel & Accommodation 4) Grants & Sponsors 5) Fundraising 6) Summary.
A6: Registration | B6: Enter your headcount, the two flat iGEM team fees (Registration and Finalization — confirmed once per team, not per person), and the three per-delegate Jamboree fee tiers (Early Bird / Standard / Late — always confirm current amounts on the official iGEM website, they change every year). Then tell it which tier you plan to register under.
A7: Lab Budget | B7: List every reagent, kit, consumable or piece of equipment you expect to need. Mark an item "Y" under 'Covered in kind?' once a sponsor confirms they will provide it — its cost then drops out of the cash total automatically.
A8: Travel & Accommodation | B8: Estimate flights, nights of accommodation and other costs (visas, insurance, local transport) for the team members attending the Grand Jamboree.
A9: Grants & Sponsors | B9: Track grants awarded (e.g. Promega's iGEM grant), confirmed cash sponsorship, and in-kind sponsorship value (for your own records — in-kind value is already excluded from the Lab Budget cash total, so it is not subtracted again in the Summary).
A10: Fundraising | B10: Log the net income (revenue minus costs) of activities such as your Christmas hamper raffle or fundraising party.
A11: Summary | B11: Pulls every sheet together into one number: the remaining gap you still need to cover. Update it as the year goes on — it is meant to be a living document, not a one-off calculation.

Sheet Registration
A1: Registration Budget
A3: Number of team members | B3: 10
A4: Additional attendees (instructors, advisors) | B4: 2
A5: Total attendees | B5: =B3+B4 -> 12
A7: iGEM Team Fees (one-time, per team — not multiplied by headcount)
A8: Fee | B8: Amount (€)
A9: iGEM Fee — Registration | B9: 4950
A10: iGEM Fee — Finalization | B10: 2750
A11: Total team fees | B11: =SUM(B9:B10) -> 7700
A12: Team-level fees billed once by iGEM HQ, regardless of headcount — confirm current amounts and payment deadlines on the official iGEM registration page.
A14: Per-Delegate Jamboree Registration
A15: Deadline | B15: Fee per person (€) | C15: Attendees | D15: Subtotal (€)
A16: Early Bird | B16: 450 | C16: =$B$5 -> 12 | D16: =B16*C16 -> 5400
A17: Standard | B17: 550 | C17: =$B$5 -> 12 | D17: =B17*C17 -> 6600
A18: Late | B18: 650 | C18: =$B$5 -> 12 | D18: =B18*C18 -> 7800
A19: Fees above are illustrative placeholders — always confirm the current amounts and dates on the official iGEM registration page before budgeting.
A21: Which tier will you register under? | B21: Standard
A22: Type exactly: Early Bird, Standard, or Late.
A24: Per-delegate registration cost to budget | B24: =INDEX(D16:D18,MATCH(B21,A16:A18,0)) -> 6600
A26: TOTAL REGISTRATION (team fees + per-delegate) | B26: =B11+B24 -> 14300

Sheet Lab Budget
A1: Lab Budget
A3: Item | B3: Category | C3: Unit cost (€) | D3: Quantity | E3: Subtotal (€) | F3: Covered in kind? (Y/N) | G3: Cash needed (€) | H3: Notes / Sponsor
A4: Restriction enzymes | B4: Reagents | C4: 45 | D4: 3 | E4: =C4*D4 -> 135 | F4: N | G4: =IF(F4="Y",0,E4) -> 135 | H4: Ordered via lab supplier
A5: PCR kit | B5: Reagents | C5: 180 | D5: 1 | E5: =C5*D5 -> 180 | F5: N | G5: =IF(F5="Y",0,E5) -> 180
A6: Alginate (sodium alginate) | B6: Reagents | C6: 60 | D6: 2 | E6: =C6*D6 -> 120 | F6: Y | G6: =IF(F6="Y",0,E6) -> 0 | H6: Donated by [Sponsor]
A7: Sequencing (Sanger, x20) | B7: Services | C7: 12 | D7: 20 | E7: =C7*D7 -> 240 | F7: N | G7: =IF(F7="Y",0,E7) -> 240
E8: =C8*D8 -> 0 | G8: =IF(F8="Y",0,E8) -> 0
E9: =C9*D9 -> 0 | G9: =IF(F9="Y",0,E9) -> 0
E10: =C10*D10 -> 0 | G10: =IF(F10="Y",0,E10) -> 0
E11: =C11*D11 -> 0 | G11: =IF(F11="Y",0,E11) -> 0
E12: =C12*D12 -> 0 | G12: =IF(F12="Y",0,E12) -> 0
E13: =C13*D13 -> 0 | G13: =IF(F13="Y",0,E13) -> 0
E14: =C14*D14 -> 0 | G14: =IF(F14="Y",0,E14) -> 0
E15: =C15*D15 -> 0 | G15: =IF(F15="Y",0,E15) -> 0
E16: =C16*D16 -> 0 | G16: =IF(F16="Y",0,E16) -> 0
E17: =C17*D17 -> 0 | G17: =IF(F17="Y",0,E17) -> 0
E18: =C18*D18 -> 0 | G18: =IF(F18="Y",0,E18) -> 0
E19: =C19*D19 -> 0 | G19: =IF(F19="Y",0,E19) -> 0
A21: TOTAL | E21: =SUM(E4:E19) -> 675 | F21: =SUMIF(F4:F19,"Y",E4:E19) -> 120 | G21: =SUM(G4:G19) -> 555
A23: Column F ('Covered in kind?') is where you record sponsor donations. Any item marked 'Y' drops out of the 'Cash needed' total automatically.

Sheet Travel & Accommodation
A1: Travel & Accommodation
A3: Number of people travelling to the Grand Jamboree | B3: 6
A4: Flight cost per person (€) | B4: 250
A5: Nights of accommodation | B5: 5
A6: Accommodation cost per person per night (€) | B6: 60
A7: Other costs per person — visa, insurance, local transport (€) | B7: 50
A9: Total flights | B9: =B3*B4 -> 1500
A10: Total accommodation | B10: =B3*B5*B6 -> 1800
A11: Total other costs | B11: =B3*B7 -> 300
A13: TOTAL TRAVEL & ACCOMMODATION | B13: =SUM(B9:B11) -> 3600
A15: The Grand Jamboree location changes each year — check the official iGEM announcement before estimating flights.

Sheet Grants & Sponsors
A1: Grants & Sponsors
A3: Grants
A4: Grant name | B4: Amount awarded (€)
A5: Promega iGEM Grant | B5: 1500
A10: Total grants | B10: =SUM(B5:B9) -> 1500
A12: Cash sponsors
A13: Sponsor name | B13: Amount (€)
A19: Total cash sponsors | B19: =SUM(B14:B18) -> 0
A21: In-kind sponsors (for your records)
A22: Sponsor name | B22: Estimated value (€)
A23: Fluidmechanical | B23: 400
A24: Doxa Microfluidics | B24: 300
A25: Soluciones Dehesa Sana | B25: 200
A28: Total in-kind value | B28: =SUM(B23:B27) -> 900
A30: In-kind value is informational only: it is already reflected in the 'Cash needed' total on the Lab Budget sheet, so it is not subtracted again in the Summary.

Sheet Fundraising
A1: Fundraising Activities
A3: Activity | B3: Revenue (€) | C3: Costs (€) | D3: Net (€)
A4: Christmas Hamper Raffle | D4: =B4-C4 -> 0
A5: Fundraising Party | D5: =B5-C5 -> 0
D6: =B6-C6 -> 0
A8: TOTAL NET FUNDRAISING | D8: =SUM(D4:D6) -> 0

Sheet Summary
A1: Budget Summary
A3: Registration (team fees + per-delegate) | B3: =Registration!B26 -> 14300
A4: Lab budget (cash needed) | B4: ='Lab Budget'!G21 -> 555
A5: Travel & accommodation | B5: ='Travel & Accommodation'!B13 -> 3600
A7: TOTAL FUNDING NEEDED | B7: =SUM(B3:B5) -> 18455
A9: Grants awarded | B9: ='Grants & Sponsors'!B10 -> 1500
A10: Cash sponsors | B10: ='Grants & Sponsors'!B19 -> 0
A11: Net fundraising (raffle, party, etc.) | B11: =Fundraising!D8 -> 0
A13: TOTAL SECURED / RAISED | B13: =SUM(B9:B11) -> 1500
A15: REMAINING GAP TO COVER | B15: =B7-B13 -> 16955
A17: This sheet updates automatically as you fill in the other tabs. Revisit it whenever a sponsor confirms, a grant is awarded, or a cost changes.
